<?xml version="1.0" encoding="utf-8" ?>
<dwsync>
<file name="tab_03.gif" server="E:/ws/bbs7.2/" local="129391432500000000" remote="129391432500000000" />
<file name="tab_05.gif" server="E:/ws/bbs7.2/" local="129391432500000000" remote="129391432500000000" />
<file name="311.gif" server="E:/ws/bbs7.2/" local="129391432500000000" remote="129391432500000000" />
<file name="001.gif" server="E:/ws/bbs7.2/" local="129391432500000000" remote="129391432500000000" />
<file name="114.gif" server="E:/ws/bbs7.2/" local="129391432500000000" remote="129391432500000000" />
<file name="083.gif" server="E:/ws/bbs7.2/" local="129391432500000000" remote="129391432500000000" />
<file name="tab_07.gif" server="E:/ws/bbs7.2/" local="129391432500000000" remote="129391432500000000" />
<file name="tab_12.gif" server="E:/ws/bbs7.2/" local="129391432500000000" remote="129391432500000000" />
<file name="tab_14.gif" server="E:/ws/bbs7.2/" local="129391432500000000" remote="129391432500000000" />
<file name="tab_16.gif" server="E:/ws/bbs7.2/" local="129391432500000000" remote="129391432500000000" />
<file name="tab_20.gif" server="E:/ws/bbs7.2/" local="129391432500000000" remote="129391432500000000" />
<file name="tab_21.gif" server="E:/ws/bbs7.2/" local="129391432500000000" remote="129391432500000000" />
<file name="tab_22.gif" server="E:/ws/bbs7.2/" local="129391432500000000" remote="129391432500000000" />
</dwsync>